{
  "build": {
    "content": [
      {
        "files": [
          "**/*.md",
          "**/*.yml"
        ],
        "src": "docs-ref-autogen",
        "exclude": [
          "**/obj/**",
          "**/includes/**",
          "README.md",
          "LICENSE",
          "LICENSE-CODE",
          "ThirdPartyNotices"
        ]
      }
    ],
    "resource": [
    ],
    "overwrite": [],
    "externalReference": [],
    "globalMetadata": {},
    "fileMetadata": {
      "ms.topic": {
        "docs-ref-autogen/**": "reference"
      }
    },
    "template": [],
    "dest": "azure-iot-docs-sdk-typescript"
  }
}